[
  {
    "id": null,
    "title": "Quiz1",
    "questions": [
      {
        "id": null,
        "question": "What year did World War II end?",
        "answers": [
          { "id": null, "content": "1941", "isValid": false },
          { "id": null, "content": "1945", "isValid": true },
          { "id": null, "content": "1939", "isValid": false },
          { "id": null, "content": "1950", "isValid": false }
        ],
        "timeToAnswer": 10
      },
      {
        "id": null,
        "question": "Who was the first president of the United States?",
        "answers": [
          { "id": null, "content": "Abraham Lincoln", "isValid": false },
          { "id": null, "content": "George Washington", "isValid": true },
          { "id": null, "content": "Thomas Jefferson", "isValid": false },
          { "id": null, "content": "John Adams", "isValid": false }
        ],
        "timeToAnswer": 10
      },
      {
        "id": null,
        "question": "Where did the Industrial Revolution begin?",
        "answers": [
          { "id": null, "content": "France", "isValid": false },
          { "id": null, "content": "United States", "isValid": false },
          { "id": null, "content": "Germany", "isValid": false },
          { "id": null, "content": "United Kingdom", "isValid": true }
        ],
        "timeToAnswer": 10
      },
      {
        "id": null,
        "question": "What empire was ruled by Genghis Khan?",
        "answers": [
          { "id": null, "content": "Roman Empire", "isValid": false },
          { "id": null, "content": "Ottoman Empire", "isValid": false },
          { "id": null, "content": "Mongol Empire", "isValid": true },
          { "id": null, "content": "British Empire", "isValid": false }
        ],
        "timeToAnswer": 10
      },
      {
        "id": null,
        "question": "What was the primary writing system of ancient Egypt?",
        "answers": [
          { "id": null, "content": "Cuneiform", "isValid": false },
          { "id": null, "content": "Hieroglyphics", "isValid": true },
          { "id": null, "content": "Runes", "isValid": false },
          { "id": null, "content": "Latin", "isValid": false }
        ],
        "timeToAnswer": 10
      }
    ],
    "categories": [{ "id": 1, "name": "History" }]
  },
  {
    "id": null,
    "title": "Quiz2",
    "questions": [
      {
        "id": null,
        "question": "What does RAM stand for in computing?",
        "answers": [
          { "id": null, "content": "Random Access Memory", "isValid": true },
          { "id": null, "content": "Read Access Module", "isValid": false },
          { "id": null, "content": "Real Application Mode", "isValid": false },
          { "id": null, "content": "Read And Modify", "isValid": false }
        ],
        "timeToAnswer": 40
      },
      {
        "id": null,
        "question": "What is the main purpose of a CPU?",
        "answers": [
          { "id": null, "content": "Store data", "isValid": false },
          { "id": null, "content": "Process instructions", "isValid": true },
          { "id": null, "content": "Transfer data", "isValid": false },
          { "id": null, "content": "Connect networks", "isValid": false }
        ],
        "timeToAnswer": 50
      },
      {
        "id": null,
        "question": "Which language is primarily used for web development?",
        "answers": [
          { "id": null, "content": "Java", "isValid": false },
          { "id": null, "content": "Python", "isValid": false },
          { "id": null, "content": "JavaScript", "isValid": true },
          { "id": null, "content": "C++", "isValid": false }
        ],
        "timeToAnswer": 30
      },
      {
        "id": null,
        "question": "Which company created the Windows operating system?",
        "answers": [
          { "id": null, "content": "Apple", "isValid": false },
          { "id": null, "content": "Google", "isValid": false },
          { "id": null, "content": "Microsoft", "isValid": true },
          { "id": null, "content": "IBM", "isValid": false }
        ],
        "timeToAnswer": 25
      },
      {
        "id": null,
        "question": "What is open-source software?",
        "answers": [
          { "id": null, "content": "Software only available for purchase", "isValid": false },
          { "id": null, "content": "Software with accessible source code", "isValid": true },
          { "id": null, "content": "Software restricted to a single user", "isValid": false },
          { "id": null, "content": "Software that requires a license", "isValid": false }
        ],
        "timeToAnswer": 45
      }
    ],
    "categories": [{ "id": 2, "name": "Computer Science" }]
  },
  {
    "id": null,
    "title": "Quiz3",
    "questions": [
      {
        "id": null,
        "question": "What is the value of π (pi) rounded to two decimal places?",
        "answers": [
          { "id": null, "content": "3.00", "isValid": false },
          { "id": null, "content": "3.14", "isValid": true },
          { "id": null, "content": "3.13", "isValid": false },
          { "id": null, "content": "3.15", "isValid": false }
        ],
        "timeToAnswer": 15
      },
      {
        "id": null,
        "question": "What is the formula for the area of a circle?",
        "answers": [
          { "id": null, "content": "πr^2", "isValid": true },
          { "id": null, "content": "2πr", "isValid": false },
          { "id": null, "content": "r^2", "isValid": false },
          { "id": null, "content": "πd", "isValid": false }
        ],
        "timeToAnswer": 25
      },
      {
        "id": null,
        "question": "What is the square root of 64?",
        "answers": [
          { "id": null, "content": "6", "isValid": false },
          { "id": null, "content": "8", "isValid": true },
          { "id": null, "content": "10", "isValid": false },
          { "id": null, "content": "7", "isValid": false }
        ],
        "timeToAnswer": 20
      },
      {
        "id": null,
        "question": "What is 9 multiplied by 9?",
        "answers": [
          { "id": null, "content": "81", "isValid": true },
          { "id": null, "content": "72", "isValid": false },
          { "id": null, "content": "90", "isValid": false },
          { "id": null, "content": "99", "isValid": false }
        ],
        "timeToAnswer": 10
      },
      {
        "id": null,
        "question": "What is 15% of 200?",
        "answers": [
          { "id": null, "content": "25", "isValid": false },
          { "id": null, "content": "30", "isValid": true },
          { "id": null, "content": "35", "isValid": false },
          { "id": null, "content": "40", "isValid": false }
        ],
        "timeToAnswer": 15
      }
    ],
    "categories": [{ "id": 3, "name": "Math" }]
  },
  {
    "id": null,
    "title": "Quiz4",
    "questions": [
      {
        "id": null,
        "question": "Which organ in the human body produces insulin?",
        "answers": [
          { "id": null, "content": "Liver", "isValid": false },
          { "id": null, "content": "Pancreas", "isValid": true },
          { "id": null, "content": "Kidneys", "isValid": false },
          { "id": null, "content": "Stomach", "isValid": false }
        ],
        "timeToAnswer": 20
      },
      {
        "id": null,
        "question": "What is the basic unit of life?",
        "answers": [
          { "id": null, "content": "Tissue", "isValid": false },
          { "id": null, "content": "Cell", "isValid": true },
          { "id": null, "content": "Organ", "isValid": false },
          { "id": null, "content": "Molecule", "isValid": false }
        ],
        "timeToAnswer": 25
      },
      {
        "id": null,
        "question": "What part of the cell contains genetic material?",
        "answers": [
          { "id": null, "content": "Cytoplasm", "isValid": false },
          { "id": null, "content": "Nucleus", "isValid": true },
          { "id": null, "content": "Cell Membrane", "isValid": false },
          { "id": null, "content": "Ribosome", "isValid": false }
        ],
        "timeToAnswer": 30
      },
      {
        "id": null,
        "question": "What type of organism is a bacterium?",
        "answers": [
          { "id": null, "content": "Prokaryote", "isValid": true },
          { "id": null, "content": "Eukaryote", "isValid": false },
          { "id": null, "content": "Fungi", "isValid": false },
          { "id": null, "content": "Virus", "isValid": false }
        ],
        "timeToAnswer": 25
      },
      {
        "id": null,
        "question": "Which organelle is known as the powerhouse of the cell?",
        "answers": [
          { "id": null, "content": "Nucleus", "isValid": false },
          { "id": null, "content": "Mitochondria", "isValid": true },
          { "id": null, "content": "Ribosome", "isValid": false },
          { "id": null, "content": "Endoplasmic Reticulum", "isValid": false }
        ],
        "timeToAnswer": 15
      }
    ],
    "categories": [{ "id": 4, "name": "Biology" }]
  },
  {
    "id": null,
    "title": "Quiz5",
    "questions": [
      {
        "id": null,
        "question": "What is the chemical symbol for gold?",
        "answers": [
          { "id": null, "content": "Ag", "isValid": false },
          { "id": null, "content": "Au", "isValid": true },
          { "id": null, "content": "Gd", "isValid": false },
          { "id": null, "content": "Ga", "isValid": false }
        ],
        "timeToAnswer": 10
      },
      {
        "id": null,
        "question": "What is H2O commonly known as?",
        "answers": [
          { "id": null, "content": "Oxygen", "isValid": false },
          { "id": null, "content": "Water", "isValid": true },
          { "id": null, "content": "Hydrogen Peroxide", "isValid": false },
          { "id": null, "content": "Acid", "isValid": false }
        ],
        "timeToAnswer": 15
      },
      {
        "id": null,
        "question": "What is the main gas found in the air we breathe?",
        "answers": [
          { "id": null, "content": "Oxygen", "isValid": false },
          { "id": null, "content": "Nitrogen", "isValid": true },
          { "id": null, "content": "Carbon Dioxide", "isValid": false },
          { "id": null, "content": "Helium", "isValid": false }
        ],
        "timeToAnswer": 20
      },
      {
        "id": null,
        "question": "What is the pH level of pure water?",
        "answers": [
          { "id": null, "content": "0", "isValid": false },
          { "id": null, "content": "7", "isValid": true },
          { "id": null, "content": "14", "isValid": false },
          { "id": null, "content": "3", "isValid": false }
        ],
        "timeToAnswer": 25
      },
      {
        "id": null,
        "question": "What element has the atomic number 6?",
        "answers": [
          { "id": null, "content": "Nitrogen", "isValid": false },
          { "id": null, "content": "Carbon", "isValid": true },
          { "id": null, "content": "Oxygen", "isValid": false },
          { "id": null, "content": "Hydrogen", "isValid": false }
        ],
        "timeToAnswer": 20
      }
    ],
    "categories": [{ "id": 5, "name": "Chemistry" }]
  },
  {
    "id": null,
    "title": "Quiz6",
    "questions": [
      {
        "id": null,
        "question": "Which exercise targets the biceps?",
        "answers": [
          { "id": null, "content": "Squat", "isValid": false },
          { "id": null, "content": "Bicep curl", "isValid": true },
          { "id": null, "content": "Leg press", "isValid": false },
          { "id": null, "content": "Bench press", "isValid": false }
        ],
        "timeToAnswer": 15
      },
      {
        "id": null,
        "question": "What muscle group does the plank exercise primarily target?",
        "answers": [
          { "id": null, "content": "Legs", "isValid": false },
          { "id": null, "content": "Core", "isValid": true },
          { "id": null, "content": "Arms", "isValid": false },
          { "id": null, "content": "Back", "isValid": false }
        ],
        "timeToAnswer": 20
      },
      {
        "id": null,
        "question": "Which exercise is best for cardiovascular endurance?",
        "answers": [
          { "id": null, "content": "Jump rope", "isValid": true },
          { "id": null, "content": "Deadlift", "isValid": false },
          { "id": null, "content": "Shoulder press", "isValid": false },
          { "id": null, "content": "Bench press", "isValid": false }
        ],
        "timeToAnswer": 25
      },
      {
        "id": null,
        "question": "Which type of stretching is recommended before a workout?",
        "answers": [
          { "id": null, "content": "Static stretching", "isValid": false },
          { "id": null, "content": "Dynamic stretching", "isValid": true },
          { "id": null, "content": "Ballistic stretching", "isValid": false },
          { "id": null, "content": "Isometric stretching", "isValid": false }
        ],
        "timeToAnswer": 15
      },
      {
        "id": null,
        "question": "What is the target heart rate zone for most effective fat burning?",
        "answers": [
          { "id": null, "content": "30-40% of max heart rate", "isValid": false },
          { "id": null, "content": "60-70% of max heart rate", "isValid": true },
          { "id": null, "content": "80-90% of max heart rate", "isValid": false },
          { "id": null, "content": "50-60% of max heart rate", "isValid": false }
        ],
        "timeToAnswer": 30
      }
    ],
    "categories": [{ "id": 6, "name": "Gym" }]
  },
  {
    "id": null,
    "title": "Quiz7",
    "questions": [
      {
        "id": null,
        "question": "How many players are on the field per team in a soccer match?",
        "answers": [
          { "id": null, "content": "9", "isValid": false },
          { "id": null, "content": "11", "isValid": true },
          { "id": null, "content": "13", "isValid": false },
          { "id": null, "content": "15", "isValid": false }
        ],
        "timeToAnswer": 10
      },
      {
        "id": null,
        "question": "What is a penalty kick awarded for in soccer?",
        "answers": [
          { "id": null, "content": "A player crossing midfield", "isValid": false },
          { "id": null, "content": "A foul inside the penalty box", "isValid": true },
          { "id": null, "content": "A goal", "isValid": false },
          { "id": null, "content": "Offside position", "isValid": false }
        ],
        "timeToAnswer": 20
      },
      {
        "id": null,
        "question": "Which country won the first World Cup in 1930?",
        "answers": [
          { "id": null, "content": "Brazil", "isValid": false },
          { "id": null, "content": "Uruguay", "isValid": true },
          { "id": null, "content": "Germany", "isValid": false },
          { "id": null, "content": "Argentina", "isValid": false }
        ],
        "timeToAnswer": 30
      },
      {
        "id": null,
        "question": "What does 'offside' mean in soccer?",
        "answers": [
          { "id": null, "content": "Player near opponent's goal without ball", "isValid": false },
          { "id": null, "content": "Player nearer to opponent's goal line than the second-last opponent when ball is passed", "isValid": true },
          { "id": null, "content": "Goalkeeper out of goal area", "isValid": false },
          { "id": null, "content": "Player crossing the centerline", "isValid": false }
        ],
        "timeToAnswer": 25
      },
      {
        "id": null,
        "question": "What is the term for scoring three goals in one game?",
        "answers": [
          { "id": null, "content": "Triple", "isValid": false },
          { "id": null, "content": "Hat-trick", "isValid": true },
          { "id": null, "content": "Three-peat", "isValid": false },
          { "id": null, "content": "Hattrick", "isValid": false }
        ],
        "timeToAnswer": 15
      }
    ],
    "categories": [{ "id": 7, "name": "Football" }]
  }
]
